{
"type": "FeatureCollection",
"features": [
{
  "type": "Feature",
  "id": "node/8320771141",
  "properties": {
    "addr:city": "Zürich",
    "addr:housenumber": "84",
    "addr:postcode": "8001",
    "addr:street": "Hirschengraben",
    "healthcare": "centre",
    "healthcare:speciality": "vaccination",
    "name": "Impfzentrum Reisezentrum Zürich",
    "note": "Für Schutz & Rettung u.a einsatzrelevant.",
    "opening_hours": "Mo-Fr 09:00-17:00",
    "operator": "Universität Zürich",
    "phone": "0800 33 66 55",
    "vaccination": "covid19",
    "website": "https://coronazentrum.uzh.ch/",
    "id": "node/8320771141"
  },
  "geometry": {
    "type": "Point",
    "coordinates": [
      8.545448,
      47.3759572
    ]
  }
}
]
}
